cmdy/__init__.py
cmdy/cmdy.py
cmdy/cmdy_bakeable.py
cmdy/cmdy_defaults.py
cmdy/cmdy_exceptions.py
cmdy/cmdy_plugin.py
cmdy/cmdy_plugins/__init__.py
cmdy/cmdy_plugins/fg.py
cmdy/cmdy_plugins/iter.py
cmdy/cmdy_plugins/pipe.py
cmdy/cmdy_plugins/redirect.py
cmdy/cmdy_plugins/value.py
cmdy/cmdy_result.py
cmdy/cmdy_utils.py
cmdy-0.5.5.dist-info/LICENSE
cmdy-0.5.5.dist-info/METADATA
cmdy-0.5.5.dist-info/WHEEL
cmdy-0.5.5.dist-info/RECORD
