Metadata-Version: 2.1
Name: cmdy
Version: 0.5.5
Summary: Shell language to run command in python
Home-page: https://github.com/pwwang/cmdy
License: MIT
Author: pwwang
Author-email: pwwang@pwwang.com
Requires-Python: >=3.7,<4.0
Classifier: License :: OSI Approved :: MIT License
Classifier: Programming Language :: Python :: 3
Classifier: Programming Language :: Python :: 3.7
Classifier: Programming Language :: Python :: 3.8
Classifier: Programming Language :: Python :: 3.9
Classifier: Programming Language :: Python :: 3.10
Classifier: Programming Language :: Python :: 3.11
Requires-Dist: curio (>=1.6,<2.0)
Requires-Dist: python-simpleconf[toml] (>=0.6,<0.7)
Requires-Dist: varname (>=0.10,<0.11) ; python_version < "3.8"
Requires-Dist: varname (>=0.11,<0.12) ; python_version >= "3.8" and python_version < "4.0"
Project-URL: Repository, https://github.com/pwwang/cmdy
